iota_sdk-1.1.4.dist-info/METADATA
iota_sdk-1.1.4.dist-info/WHEEL
iota_sdk.libs/libudev-f72ada15.so.1
iota_sdk/py.typed
iota_sdk/secret_manager/secret_manager.py
iota_sdk/types/payload.py
iota_sdk/types/feature.py
iota_sdk/types/native_token.py
iota_sdk/types/signature.py
iota_sdk/types/input.py
iota_sdk/types/transaction.py
iota_sdk/types/balance.py
iota_sdk/types/output.py
iota_sdk/types/client_options.py
iota_sdk/types/irc_27.py
iota_sdk/types/unlock.py
iota_sdk/types/transaction_options.py
iota_sdk/types/node_info.py
iota_sdk/types/address.py
iota_sdk/types/transaction_data.py
iota_sdk/types/output_id.py
iota_sdk/types/common.py
iota_sdk/types/filter_options.py
iota_sdk/types/network_info.py
iota_sdk/types/token_scheme.py
iota_sdk/types/consolidation_params.py
iota_sdk/types/utxo_changes.py
iota_sdk/types/block_builder_options.py
iota_sdk/types/burn.py
iota_sdk/types/event.py
iota_sdk/types/send_params.py
iota_sdk/types/irc_30.py
iota_sdk/types/output_data.py
iota_sdk/types/block.py
iota_sdk/types/output_params.py
iota_sdk/types/unlock_condition.py
iota_sdk/prefix_hex.py
iota_sdk/client/_node_core_api.py
iota_sdk/client/client.py
iota_sdk/client/_utils.py
iota_sdk/client/_node_indexer_api.py
iota_sdk/client/_high_level_api.py
iota_sdk/__init__.py
iota_sdk/utils.py
iota_sdk/external.py
iota_sdk/wallet/account.py
iota_sdk/wallet/prepared_transaction.py
iota_sdk/wallet/common.py
iota_sdk/wallet/wallet.py
iota_sdk/wallet/sync_options.py
iota_sdk/iota_sdk.cpython-311-x86_64-linux-gnu.so
iota_sdk-1.1.4.dist-info/RECORD
