Metadata-Version: 2.3
Name: iota-sdk
Version: 1.1.4
Requires-Dist: dacite >=1.8.1
Requires-Dist: pyhumps >=3.8.0
Summary: Python bindings for the IOTA SDK library
Keywords: iota,client,wallet,transaction,python
Home-Page: https://www.iota.org/
Author: IOTA Stiftung
License: Apache-2.0
Project-URL: Source Code, https://github.com/iotaledger/iota-sdk
